django_freakyfunkyfonts-1.4.1.dist-info/licenses/LICENCE
freakyfunkyfonts/__init__.py
freakyfunkyfonts/middleware.py
freakyfunkyfonts/settings.py
django_freakyfunkyfonts-1.4.1.dist-info/METADATA
django_freakyfunkyfonts-1.4.1.dist-info/WHEEL
django_freakyfunkyfonts-1.4.1.dist-info/top_level.txt
django_freakyfunkyfonts-1.4.1.dist-info/RECORD
