Metadata-Version: 2.4
Name: django-freakyfunkyfonts
Version: 1.4.1
Summary: Django middleware for when you want your fonts to get freaky.
Author: Naitsabot
License-Expression: MIT
Project-URL: Homepage, https://github.com/Naitsabot/django-freakyfunkyfonts
Project-URL: Source, https://github.com/Naitsabot/django-freakyfunkyfonts
Project-URL: Issues, https://github.com/Naitsabot/django-freakyfunkyfonts/issues
Keywords: django,middleware,fonts,html
Classifier: Framework :: Django
Classifier: Framework :: Django :: 4.2
Classifier: Framework :: Django :: 5.0
Classifier: Programming Language :: Python :: 3
Classifier: Programming Language :: Python :: 3.10
Classifier: Programming Language :: Python :: 3.11
Classifier: Programming Language :: Python :: 3.12
Classifier: Operating System :: OS Independent
Requires-Python: >=3.10
License-File: LICENCE
Requires-Dist: beautifulsoup4>=4.13.5
Dynamic: license-file
